palanteer_scripting/__init__.py
palanteer_scripting/_cextension.cp38-win_amd64.pyd
palanteer_scripting/_scripting.py
palanteer_scripting-0.8.0.dist-info/LICENSE
palanteer_scripting-0.8.0.dist-info/METADATA
palanteer_scripting-0.8.0.dist-info/WHEEL
palanteer_scripting-0.8.0.dist-info/top_level.txt
palanteer_scripting-0.8.0.dist-info/RECORD
