Metadata-Version: 2.1
Name: palanteer_scripting
Version: 0.8.0
Summary: Palanteer scripting module
Home-page: https://github.com/dfeneyrou/palanteer
Author: Damien Feneyrou
Author-email: dfeneyrou@gmail.com
License: AGPLv3+
Classifier: Intended Audience :: Developers
Classifier: Intended Audience :: Science/Research
Classifier: License :: OSI Approved :: GNU Affero General Public License v3 or later (AGPLv3+)
Classifier: Development Status :: 4 - Beta
Classifier: Programming Language :: Python :: 3
Classifier: Programming Language :: Python :: 3.7
Classifier: Programming Language :: Python :: 3.8
Classifier: Programming Language :: Python :: 3.9
Classifier: Programming Language :: Python :: 3.10
Classifier: Programming Language :: Python :: 3.11
Classifier: Programming Language :: Python :: Implementation :: CPython
Classifier: Operating System :: Microsoft :: Windows :: Windows 10
Classifier: Operating System :: POSIX :: Linux
Classifier: Topic :: Software Development
Classifier: Topic :: Software Development :: Testing
Requires-Python: >=3.7
License-File: LICENSE
